investimentos/__init__.py
investimentos/calculos.py
investimentos/dados.py
investimentos/visualizacao.py
investimentos_package-1.0.0.dist-info/METADATA
investimentos_package-1.0.0.dist-info/WHEEL
investimentos_package-1.0.0.dist-info/top_level.txt
investimentos_package-1.0.0.dist-info/RECORD
