Metadata-Version: 2.4
Name: investimentos-package
Version: 1.0.0
Summary: Uma biblioteca para análise de investimentos
Home-page: https://github.com/tadrianonet/investimentos
Author: Rodrigo  Raiche
Author-email: raicheposia@gmail.com
License: MIT
Dynamic: author
Dynamic: author-email
Dynamic: description
Dynamic: description-content-type
Dynamic: home-page
Dynamic: license
Dynamic: summary
